qlink/__init__.py
qlink/dataset_cleaning.py
qlink/dataset_processing.py
qlink/dataset_receiving.py
qlink/duplicate_searching.py
qlink/duplicates_merger.py
qlink/indexation.py
qlink/log_functions.py
qlink/matrix_calculation.py
qlink/parsers.py
qlink/record_metrics.py
qlink/record_processing.py
qlink/result_estimation.py
qlink/result_saving.py
qlink/utils.py
qlink-0.1a1.dist-info/DESCRIPTION.rst
qlink-0.1a1.dist-info/METADATA
qlink-0.1a1.dist-info/RECORD
qlink-0.1a1.dist-info/WHEEL
qlink-0.1a1.dist-info/metadata.json
qlink-0.1a1.dist-info/top_level.txt
